<?xml version="1.0" encoding="UTF-8"?>
<data>
<settings>
<resistance>3.769911184308</resistance>

<Tau>1.0</Tau>
<KBT>1.0</KBT>
<Linear_Const>5.0</Linear_Const>
<Area_Const>1.5</Area_Const>
<Bend_Const>0.5</Bend_Const>
<LJ_Eps>20</LJ_Eps>
<LJ_Rmin>3.5</LJ_Rmin>
<LJ_Rmax>3.90512484</LJ_Rmax>
<LJ_Const>1.5</LJ_Const>
<LJ_X>0.0</LJ_X>
<LJ_Y>0.0</LJ_Y>
<LJ_Z>-1.5</LJ_Z>

</settings>
    <nodes default-mass="1.0">
    <node>	-0.97625212	-0.216637483	1.00000	</node>
<node>	-0.999825586	-0.018676112	1.00000	</node>
<node>	-0.995696807	0.092670749	1.00000	</node>
<node>	-0.957102842	0.289748423	1.00000	</node>
<node>	-0.907691193	-0.419638766	1.00000	</node>
<node>	-0.946444641	-0.322866135	1.00000	</node>
<node>	-0.88389292	-0.249609021	1.00000	</node>
<node>	-0.992528205	-0.122015412	1.00000	</node>
<node>	-0.901550247	-0.05627455	1.00000	</node>
<node>	-0.922375552	0.03491769	1.00000	</node>
<node>	-0.895369352	0.125079191	1.00000	</node>
<node>	-0.980657341	0.195732415	1.00000	</node>
<node>	-0.86362568	0.3179037	1.00000	</node>
<node>	-0.918807439	0.39470608	1.00000	</node>
<node>	-0.871539076	0.490326054	1.00000	</node>
<node>	-0.803868951	-0.594806445	1.00000	</node>
<node>	-0.859847458	-0.510551025	1.00000	</node>
<node>	-0.797663779	-0.42141268	1.00000	</node>
<node>	-0.842307703	-0.333888948	1.00000	</node>
<node>	-0.792474364	-0.238613803	1.00000	</node>
<node>	-0.871762189	-0.153184802	1.00000	</node>
<node>	-0.798494563	-0.063232442	1.00000	</node>
<node>	-0.834809267	0.032842855	1.00000	</node>
<node>	-0.792463445	0.127454911	1.00000	</node>
<node>	-0.858978532	0.22074688	1.00000	</node>
<node>	-0.774748058	0.303263589	1.00000	</node>
<node>	-0.816370011	0.400740506	1.00000	</node>
<node>	-0.765762855	0.486673482	1.00000	</node>
<node>	-0.814485868	0.580183393	1.00000	</node>
<node>	-0.74752355	0.664235305	1.00000	</node>
<node>	-0.672013331	-0.740539049	1.00000	</node>
<node>	-0.741145116	-0.671344857	1.00000	</node>
<node>	-0.689989874	-0.591070476	1.00000	</node>
<node>	-0.746797666	-0.507109323	1.00000	</node>
<node>	-0.689511914	-0.420112643	1.00000	</node>
<node>	-0.740155526	-0.33067735	1.00000	</node>
<node>	-0.688893441	-0.239759156	1.00000	</node>
<node>	-0.751329957	-0.150434173	1.00000	</node>
<node>	-0.691081603	-0.061425868	1.00000	</node>
<node>	-0.737670759	0.030980777	1.00000	</node>
<node>	-0.685961424	0.122065136	1.00000	</node>
<node>	-0.740358354	0.213436191	1.00000	</node>
<node>	-0.673289932	0.301479817	1.00000	</node>
<node>	-0.717017799	0.394154259	1.00000	</node>
<node>	-0.661535916	0.483759334	1.00000	</node>
<node>	-0.710322076	0.569862043	1.00000	</node>
<node>	-0.655426254	0.648653416	1.00000	</node>
<node>	-0.601889914	-0.79857907	1.00000	</node>
<node>	-0.630543459	-0.678872462	1.00000	</node>
<node>	-0.579844886	-0.598491646	1.00000	</node>
<node>	-0.635674381	-0.508170965	1.00000	</node>
<node>	-0.581614212	-0.421667365	1.00000	</node>
<node>	-0.634851682	-0.331065706	1.00000	</node>
<node>	-0.582746629	-0.241567107	1.00000	</node>
<node>	-0.639556482	-0.150985886	1.00000	</node>
<node>	-0.583512954	-0.061934458	1.00000	</node>
<node>	-0.63361853	0.029416229	1.00000	</node>
<node>	-0.57934203	0.119675935	1.00000	</node>
<node>	-0.630299179	0.210791161	1.00000	</node>
<node>	-0.569958211	0.301449991	1.00000	</node>
<node>	-0.615059134	0.393295143	1.00000	</node>
<node>	-0.559628008	0.487691665	1.00000	</node>
<node>	-0.605358324	0.576245542	1.00000	</node>
<node>	-0.567311712	0.688826776	1.00000	</node>
<node>	-0.668060631	0.744106843	1.00000	</node>
<node>	-0.590657907	0.806922076	1.00000	</node>
<node>	-0.527925959	-0.849290397	1.00000	</node>
<node>	-0.479742957	-0.786709014	1.00000	</node>
<node>	-0.532748733	-0.699686077	1.00000	</node>
<node>	-0.476251619	-0.610415696	1.00000	</node>
<node>	-0.527448285	-0.513309575	1.00000	</node>
<node>	-0.474949501	-0.425138369	1.00000	</node>
<node>	-0.5285352	-0.333022304	1.00000	</node>
<node>	-0.476190578	-0.243729046	1.00000	</node>
<node>	-0.530935247	-0.15253079	1.00000	</node>
<node>	-0.476471112	-0.063166425	1.00000	</node>
<node>	-0.527829513	0.028080356	1.00000	</node>
<node>	-0.473393098	0.118457532	1.00000	</node>
<node>	-0.523739819	0.209939644	1.00000	</node>
<node>	-0.467140109	0.301973083	1.00000	</node>
<node>	-0.513699832	0.395167789	1.00000	</node>
<node>	-0.461640005	0.492682652	1.00000	</node>
<node>	-0.510757492	0.590235405	1.00000	</node>
<node>	-0.45669159	0.683480149	1.00000	</node>
<node>	-0.501287526	0.76652914	1.00000	</node>
<node>	-0.496082657	0.8682753	1.00000	</node>
<node>	-0.366407743	-0.930454387	1.00000	</node>
<node>	-0.447062948	-0.894502499	1.00000	</node>
<node>	-0.37431461	-0.8085923	1.00000	</node>
<node>	-0.423178859	-0.704487337	1.00000	</node>
<node>	-0.370438618	-0.612910451	1.00000	</node>
<node>	-0.422858831	-0.51972428	1.00000	</node>
<node>	-0.3698104	-0.429109887	1.00000	</node>
<node>	-0.422438271	-0.33579545	1.00000	</node>
<node>	-0.36997982	-0.245998728	1.00000	</node>
<node>	-0.4236963	-0.154303045	1.00000	</node>
<node>	-0.370032327	-0.064497561	1.00000	</node>
<node>	-0.421944201	0.026910541	1.00000	</node>
<node>	-0.368101155	0.117540122	1.00000	</node>
<node>	-0.418877032	0.209495786	1.00000	</node>
<node>	-0.364768959	0.301676362	1.00000	</node>
<node>	-0.413618362	0.396252649	1.00000	</node>
<node>	-0.361484439	0.48949695	1.00000	</node>
<node>	-0.40944921	0.587536473	1.00000	</node>
<node>	-0.358261281	0.685777844	1.00000	</node>
<node>	-0.405539405	0.79254414	1.00000	</node>
<node>	-0.32471695	0.858752306	1.00000	</node>
<node>	-0.405471513	0.91410768	1.00000	</node>
<node>	-0.271228476	-0.962514994	1.00000	</node>
<node>	-0.297083683	-0.86966441	1.00000	</node>
<node>	-0.261086211	-0.788307596	1.00000	</node>
<node>	-0.320197237	-0.707930217	1.00000	</node>
<node>	-0.265294184	-0.614993181	1.00000	</node>
<node>	-0.317185784	-0.521807066	1.00000	</node>
<node>	-0.264143507	-0.430927656	1.00000	</node>
<node>	-0.316967118	-0.338534922	1.00000	</node>
<node>	-0.264237296	-0.247947144	1.00000	</node>
<node>	-0.317300302	-0.155994119	1.00000	</node>
<node>	-0.26409301	-0.065707163	1.00000	</node>
<node>	-0.316335724	0.025843151	1.00000	</node>
<node>	-0.263097223	0.116531154	1.00000	</node>
<node>	-0.314650981	0.208647202	1.00000	</node>
<node>	-0.261481845	0.299636046	1.00000	</node>
<node>	-0.311979299	0.39355811	1.00000	</node>
<node>	-0.260478841	0.484919612	1.00000	</node>
<node>	-0.310698226	0.582687071	1.00000	</node>
<node>	-0.257132382	0.669868236	1.00000	</node>
<node>	-0.295843256	0.771457368	1.00000	</node>
<node>	-0.224969028	0.872042635	1.00000	</node>
<node>	-0.29607375	0.95516508	1.00000	</node>
<node>	-0.177972338	-0.984035491	1.00000	</node>
<node>	-0.206239203	-0.881754205	1.00000	</node>
<node>	-0.15516766	-0.796203374	1.00000	</node>
<node>	-0.210004265	-0.703207749	1.00000	</node>
<node>	-0.157649341	-0.614704137	1.00000	</node>
<node>	-0.211586234	-0.523587538	1.00000	</node>
<node>	-0.158564838	-0.432209995	1.00000	</node>
<node>	-0.211310217	-0.339987854	1.00000	</node>
<node>	-0.158531367	-0.249015438	1.00000	</node>
<node>	-0.211432208	-0.157333817	1.00000	</node>
<node>	-0.158433457	-0.066647455	1.00000	</node>
<node>	-0.210909444	0.024858564	1.00000	</node>
<node>	-0.157954191	0.115454632	1.00000	</node>
<node>	-0.210108578	0.2071439	1.00000	</node>
<node>	-0.157430304	0.297553822	1.00000	</node>
<node>	-0.20922793	0.390277014	1.00000	</node>
<node>	-0.157105571	0.479220964	1.00000	</node>
<node>	-0.208369284	0.573095502	1.00000	</node>
<node>	-0.155520285	0.659374685	1.00000	</node>
<node>	-0.202378813	0.756530926	1.00000	</node>
<node>	-0.141954923	0.825242088	1.00000	</node>
<node>	-0.188910249	0.981994356	1.00000	</node>
<node>	-0.086407297	-0.996259895	1.00000	</node>
<node>	-0.108247422	-0.895116326	1.00000	</node>
<node>	-0.051107271	-0.806557185	1.00000	</node>
<node>	-0.103549426	-0.708377444	1.00000	</node>
<node>	-0.052192741	-0.616787346	1.00000	</node>
<node>	-0.105333749	-0.523932879	1.00000	</node>
<node>	-0.052786463	-0.432432257	1.00000	</node>
<node>	-0.105721315	-0.340817925	1.00000	</node>
<node>	-0.052872347	-0.249528468	1.00000	</node>
<node>	-0.105699719	-0.15807135	1.00000	</node>
<node>	-0.052804043	-0.06715194	1.00000	</node>
<node>	-0.105475203	0.024077396	1.00000	</node>
<node>	-0.052685761	0.114809573	1.00000	</node>
<node>	-0.10520379	0.205966375	1.00000	</node>
<node>	-0.052551524	0.29616199	1.00000	</node>
<node>	-0.104999848	0.387139861	1.00000	</node>
<node>	-0.052668305	0.475904047	1.00000	</node>
<node>	-0.104790351	0.566741781	1.00000	</node>
<node>	-0.051342615	0.652061726	1.00000	</node>
<node>	-0.099339252	0.740290092	1.00000	</node>
<node>	-0.048634808	0.830386477	1.00000	</node>
<node>	-0.11315228	0.91292614	1.00000	</node>
<node>	-0.060925248	0.998142332	1.00000	</node>
<node>	6.42E-05	-0.999999998	1.00000	</node>
<node>	0.086469413	-0.996254506	1.00000	</node>
<node>	-1.22E-05	-0.908436544	1.00000	</node>
<node>	0.051068031	-0.80655677	1.00000	</node>
<node>	-1.72E-05	-0.711374443	1.00000	</node>
<node>	0.052163719	-0.616787475	1.00000	</node>
<node>	-1.07E-05	-0.524434525	1.00000	</node>
<node>	0.052772197	-0.43243274	1.00000	</node>
<node>	-4.00E-06	-0.340916996	1.00000	</node>
<node>	0.052868949	-0.249528473	1.00000	</node>
<node>	-4.59E-07	-0.158350571	1.00000	</node>
<node>	0.052803483	-0.067151015	1.00000	</node>
<node>	-1.46E-06	0.023813204	1.00000	</node>
<node>	0.05267758	0.114811489	1.00000	</node>
<node>	-8.46E-06	0.205459679	1.00000	</node>
<node>	0.052522647	0.296164441	1.00000	</node>
<node>	-2.28E-05	0.386123755	1.00000	</node>
<node>	0.05259862	0.475906736	1.00000	</node>
<node>	-5.43E-05	0.563559291	1.00000	</node>
<node>	0.051196658	0.652024544	1.00000	</node>
<node>	-9.28E-05	0.740545638	1.00000	</node>
<node>	0.048558478	0.830190114	1.00000	</node>
<node>	0.000204373	0.91778409	1.00000	</node>
<node>	0.062417421	0.998050132	1.00000	</node>
<node>	0.177928916	-0.984043342	1.00000	</node>
<node>	0.10820455	-0.895109736	1.00000	</node>
<node>	0.155120038	-0.796204302	1.00000	</node>
<node>	0.103511342	-0.708378888	1.00000	</node>
<node>	0.157617426	-0.614708082	1.00000	</node>
<node>	0.105311784	-0.523934284	1.00000	</node>
<node>	0.15855013	-0.432212644	1.00000	</node>
<node>	0.10571333	-0.340818757	1.00000	</node>
<node>	0.158528166	-0.249015977	1.00000	</node>
<node>	0.10569896	-0.158070604	1.00000	</node>
<node>	0.158433289	-0.066644849	1.00000	</node>
<node>	0.105472598	0.024080298	1.00000	</node>
<node>	0.157946789	0.115460616	1.00000	</node>
<node>	0.105187384	0.20597108	1.00000	</node>
<node>	0.157402495	0.297562211	1.00000	</node>
<node>	0.104954405	0.387145216	1.00000	</node>
<node>	0.157042879	0.479222635	1.00000	</node>
<node>	0.104697743	0.566730446	1.00000	</node>
<node>	0.155427536	0.659319771	1.00000	</node>
<node>	0.099205872	0.74013394	1.00000	</node>
<node>	0.14185455	0.824971252	1.00000	</node>
<node>	0.113187861	0.91258338	1.00000	</node>
<node>	0.271137967	-0.962540494	1.00000	</node>
<node>	0.206171486	-0.881761278	1.00000	</node>
<node>	0.261024699	-0.788322849	1.00000	</node>
<node>	0.20996013	-0.703214998	1.00000	</node>
<node>	0.265257296	-0.615005221	1.00000	</node>
<node>	0.211562068	-0.523593865	1.00000	</node>
<node>	0.264127432	-0.430935225	1.00000	</node>
<node>	0.211302083	-0.339990973	1.00000	</node>
<node>	0.264234163	-0.247949447	1.00000	</node>
<node>	0.211431779	-0.157332873	1.00000	</node>
<node>	0.264093486	-0.065703414	1.00000	</node>
<node>	0.210907626	0.024864228	1.00000	</node>
<node>	0.26309092	0.116541436	1.00000	</node>
<node>	0.210093475	0.207154347	1.00000	</node>
<node>	0.261457478	0.299651303	1.00000	</node>
<node>	0.209187114	0.390287079	1.00000	</node>
<node>	0.260427385	0.484928304	1.00000	</node>
<node>	0.208298358	0.573082923	1.00000	</node>
<node>	0.257057648	0.669854445	1.00000	</node>
<node>	0.202293402	0.756450569	1.00000	</node>
<node>	0.224708296	0.872048347	1.00000	</node>
<node>	0.188012419	0.982166651	1.00000	</node>
<node>	0.366300908	-0.930496451	1.00000	</node>
<node>	0.296997924	-0.86969133	1.00000	</node>
<node>	0.374229083	-0.808630542	1.00000	</node>
<node>	0.32014257	-0.707951763	1.00000	</node>
<node>	0.370394772	-0.612934433	1.00000	</node>
<node>	0.317158193	-0.521821293	1.00000	</node>
<node>	0.369792084	-0.4291248	1.00000	</node>
<node>	0.316958206	-0.338542374	1.00000	</node>
<node>	0.36997655	-0.246004961	1.00000	</node>
<node>	0.317300153	-0.155994295	1.00000	</node>
<node>	0.370033183	-0.064493507	1.00000	</node>
<node>	0.316334886	0.02585147	1.00000	</node>
<node>	0.368096299	0.117554791	1.00000	</node>
<node>	0.314637864	0.208663487	1.00000	</node>
<node>	0.364748193	0.301700179	1.00000	</node>
<node>	0.311945426	0.393578484	1.00000	</node>
<node>	0.361438477	0.489529679	1.00000	</node>
<node>	0.310635264	0.582704243	1.00000	</node>
<node>	0.358149749	0.6858475	1.00000	</node>
<node>	0.295687006	0.771517161	1.00000	</node>
<node>	0.324423551	0.858882684	1.00000	</node>
<node>	0.295481586	0.955348435	1.00000	</node>
<node>	0.446949647	-0.894559116	1.00000	</node>
<node>	0.479647062	-0.786764796	1.00000	</node>
<node>	0.423111889	-0.704525658	1.00000	</node>
<node>	0.476199923	-0.610455621	1.00000	</node>
<node>	0.422826736	-0.519749644	1.00000	</node>
<node>	0.474928853	-0.425163922	1.00000	</node>
<node>	0.422428368	-0.33580999	1.00000	</node>
<node>	0.476186499	-0.24374086	1.00000	</node>
<node>	0.423695853	-0.154305762	1.00000	</node>
<node>	0.476471841	-0.063163313	1.00000	</node>
<node>	0.421944155	0.026920774	1.00000	</node>
<node>	0.473389156	0.118476005	1.00000	</node>
<node>	0.418866002	0.20951897	1.00000	</node>
<node>	0.467121189	0.302008332	1.00000	</node>
<node>	0.413586777	0.396288918	1.00000	</node>
<node>	0.461587403	0.49274291	1.00000	</node>
<node>	0.409372929	0.587603825	1.00000	</node>
<node>	0.456568613	0.683584442	1.00000	</node>
<node>	0.405338915	0.792672661	1.00000	</node>
<node>	0.495838043	0.868415011	1.00000	</node>
<node>	0.405111118	0.914267456	1.00000	</node>
<node>	0.527814732	-0.849359527	1.00000	</node>
<node>	0.601774187	-0.79866628	1.00000	</node>
<node>	0.53267065	-0.699745573	1.00000	</node>
<node>	0.579787396	-0.598549132	1.00000	</node>
<node>	0.527411982	-0.513349375	1.00000	</node>
<node>	0.581590366	-0.421705249	1.00000	</node>
<node>	0.528523463	-0.333045641	1.00000	</node>
<node>	0.582741182	-0.241585936	1.00000	</node>
<node>	0.530933893	-0.152537491	1.00000	</node>
<node>	0.583513066	-0.061933723	1.00000	</node>
<node>	0.527829799	0.028091247	1.00000	</node>
<node>	0.57933808	0.119696751	1.00000	</node>
<node>	0.52372922	0.209969248	1.00000	</node>
<node>	0.569938524	0.301493889	1.00000	</node>
<node>	0.513666617	0.395220923	1.00000	</node>
<node>	0.559574595	0.48776452	1.00000	</node>
<node>	0.510674507	0.590322457	1.00000	</node>
<node>	0.56719362	0.68893585	1.00000	</node>
<node>	0.501116811	0.766652791	1.00000	</node>
<node>	0.590489094	0.807045616	1.00000	</node>
<node>	0.671902026	-0.740640039	1.00000	</node>
<node>	0.630459907	-0.678950098	1.00000	</node>
<node>	0.689926594	-0.591148535	1.00000	</node>
<node>	0.635633426	-0.508226968	1.00000	</node>
<node>	0.689484346	-0.420164248	1.00000	</node>
<node>	0.634837536	-0.33109922	1.00000	</node>
<node>	0.688886222	-0.239786076	1.00000	</node>
<node>	0.639553822	-0.150997955	1.00000	</node>
<node>	0.691080838	-0.061428991	1.00000	</node>
<node>	0.633618758	0.029426156	1.00000	</node>
<node>	0.685957161	0.122085922	1.00000	</node>
<node>	0.63028809	0.210824382	1.00000	</node>
<node>	0.673270395	0.301526421	1.00000	</node>
<node>	0.61502531	0.393354649	1.00000	</node>
<node>	0.661485116	0.483833913	1.00000	</node>
<node>	0.605281842	0.576335615	1.00000	</node>
<node>	0.655332061	0.648752603	1.00000	</node>
<node>	0.66793789	0.744217021	1.00000	</node>
<node>	0.741050624	-0.671449157	1.00000	</node>
<node>	0.803794719	-0.594906757	1.00000	</node>
<node>	0.746751235	-0.507183442	1.00000	</node>
<node>	0.797631841	-0.421478693	1.00000	</node>
<node>	0.740138529	-0.330721552	1.00000	</node>
<node>	0.792465324	-0.238648739	1.00000	</node>
<node>	0.75132594	-0.15045303	1.00000	</node>
<node>	0.798492962	-0.063241725	1.00000	</node>
<node>	0.737670883	0.030987942	1.00000	</node>
<node>	0.792459308	0.127474261	1.00000	</node>
<node>	0.740347595	0.21346946	1.00000	</node>
<node>	0.774730017	0.303308895	1.00000	</node>
<node>	0.716985744	0.394214258	1.00000	</node>
<node>	0.765717898	0.486745948	1.00000	</node>
<node>	0.710255694	0.569947877	1.00000	</node>
<node>	0.747439131	0.664330299	1.00000	</node>
<node>	0.859793846	-0.510641305	1.00000	</node>
<node>	0.907655814	-0.419715288	1.00000	</node>
<node>	0.842287188	-0.33394415	1.00000	</node>
<node>	0.883881139	-0.249653221	1.00000	</node>
<node>	0.871757743	-0.153211973	1.00000	</node>
<node>	0.901548276	-0.05628827	1.00000	</node>
<node>	0.834808535	0.032846103	1.00000	</node>
<node>	0.895366283	0.125093994	1.00000	</node>
<node>	0.858969974	0.22077771	1.00000	</node>
<node>	0.863608616	0.317948575	1.00000	</node>
<node>	0.816341066	0.400799083	1.00000	</node>
<node>	0.871500386	0.490394818	1.00000	</node>
<node>	0.814427408	0.580265452	1.00000	</node>
<node>	0.946423824	-0.322927147	1.00000	</node>
<node>	0.976242306	-0.216681699	1.00000	</node>
<node>	0.992524693	-0.122043983	1.00000	</node>
<node>	0.999825325	-0.018690075	1.00000	</node>
<node>	0.922375566	0.034917179	1.00000	</node>
<node>	0.995696142	0.092677897	1.00000	</node>
<node>	0.980652935	0.195754486	1.00000	</node>
<node>	0.957091472	0.289785979	1.00000	</node>
<node>	0.918784088	0.394760428	1.00000	</node>
<node>	-0.96134838	-0.269751809	1.00000	</node>
<node>	-0.93007252	-0.233123252	1.00000	</node>
<node>	-0.984390162	-0.169326447	1.00000	</node>
<node>	-0.924007154	-0.184911142	1.00000	</node>
<node>	-0.997761197	0.036997319	1.00000	</node>
<node>	-0.996176896	-0.070345762	1.00000	</node>
<node>	-0.950687916	-0.037475331	1.00000	</node>
<node>	-0.961100569	0.008120789	1.00000	</node>
<node>	-0.959036179	0.063794219	1.00000	</node>
<node>	-0.94553308	0.10887497	1.00000	</node>
<node>	-0.988177074	0.144201582	1.00000	</node>
<node>	-0.968880092	0.242740419	1.00000	</node>
<node>	-0.910364261	0.303826062	1.00000	</node>
<node>	-0.937955141	0.342227252	1.00000	</node>
<node>	-0.908040687	0.255247652	1.00000	</node>
<node>	-0.927067917	-0.371252451	1.00000	</node>
<node>	-0.883769325	-0.465094896	1.00000	</node>
<node>	-0.852677486	-0.420525723	1.00000	</node>
<node>	-0.874999448	-0.376763857	1.00000	</node>
<node>	-0.915168781	-0.286237578	1.00000	</node>
<node>	-0.894376172	-0.328377542	1.00000	</node>
<node>	-0.863100311	-0.291748985	1.00000	</node>
<node>	-0.838183642	-0.244111412	1.00000	</node>
<node>	-0.877827554	-0.201396912	1.00000	</node>
<node>	-0.947039226	-0.089144981	1.00000	</node>
<node>	-0.932145197	-0.137600107	1.00000	</node>
<node>	-0.911962899	-0.01067843	1.00000	</node>
<node>	-0.886656218	-0.104729676	1.00000	</node>
<node>	-0.850022405	-0.059753496	1.00000	</node>
<node>	-0.868179757	-0.011715848	1.00000	</node>
<node>	-0.908872452	0.07999844	1.00000	</node>
<node>	-0.878592409	0.033880272	1.00000	</node>
<node>	-0.938013347	0.160405803	1.00000	</node>
<node>	-0.86508931	0.078961023	1.00000	</node>
<node>	-0.843916399	0.126267051	1.00000	</node>
<node>	-0.877173942	0.172913036	1.00000	</node>
<node>	-0.919817937	0.208239648	1.00000	</node>
<node>	-0.89121656	0.35630489	1.00000	</node>
<node>	-0.861302106	0.26932529	1.00000	</node>
<node>	-0.819186869	0.310583644	1.00000	</node>
<node>	-0.839997846	0.359322103	1.00000	</node>
<node>	-0.895173257	0.442516067	1.00000	</node>
<node>	-0.867588725	0.397723293	1.00000	</node>
<node>	-0.843954543	0.44553328	1.00000	</node>
<node>	-0.818650965	0.488499768	1.00000	</node>
<node>	-0.843012472	0.535254723	1.00000	</node>
<node>	-0.831858204	-0.552678735	1.00000	</node>
<node>	-0.772507034	-0.633075651	1.00000	</node>
<node>	-0.746929412	-0.59293846	1.00000	</node>
<node>	-0.775333309	-0.550957884	1.00000	</node>
<node>	-0.828755618	-0.465981853	1.00000	</node>
<node>	-0.803322562	-0.508830174	1.00000	</node>
<node>	-0.819985741	-0.377650814	1.00000	</node>
<node>	-0.772230722	-0.464261002	1.00000	</node>
<node>	-0.743587846	-0.420762662	1.00000	</node>
<node>	-0.768909652	-0.376045015	1.00000	</node>
<node>	-0.817391033	-0.286251375	1.00000	</node>
<node>	-0.791231614	-0.332283149	1.00000	</node>
<node>	-0.832118276	-0.195899302	1.00000	</node>
<node>	-0.766314945	-0.284645576	1.00000	</node>
<node>	-0.740683902	-0.239186479	1.00000	</node>
<node>	-0.77190216	-0.194523988	1.00000	</node>
<node>	-0.835128376	-0.108208622	1.00000	</node>
<node>	-0.811546073	-0.151809488	1.00000	</node>
<node>	-0.816651915	-0.015194794	1.00000	</node>
<node>	-0.77491226	-0.106833308	1.00000	</node>
<node>	-0.744788083	-0.062329155	1.00000	</node>
<node>	-0.768082661	-0.016125833	1.00000	</node>
<node>	-0.813636356	0.080148883	1.00000	</node>
<node>	-0.786240013	0.031911816	1.00000	</node>
<node>	-0.825720989	0.174100896	1.00000	</node>
<node>	-0.765067102	0.079217844	1.00000	</node>
<node>	-0.739212435	0.124760024	1.00000	</node>
<node>	-0.766410899	0.170445551	1.00000	</node>
<node>	-0.816863295	0.262005234	1.00000	</node>
<node>	-0.799668443	0.217091535	1.00000	</node>
<node>	-0.795559035	0.352002047	1.00000	</node>
<node>	-0.757553206	0.25834989	1.00000	</node>
<node>	-0.724018995	0.302371703	1.00000	</node>
<node>	-0.745882929	0.348708924	1.00000	</node>
<node>	-0.791066433	0.443706994	1.00000	</node>
<node>	-0.766693905	0.397447382	1.00000	</node>
<node>	-0.790124362	0.533428437	1.00000	</node>
<node>	-0.741390327	0.44041387	1.00000	</node>
<node>	-0.713649386	0.485216408	1.00000	</node>
<node>	-0.738042466	0.528267763	1.00000	</node>
<node>	-0.781004709	0.622209349	1.00000	</node>
<node>	-0.762403972	0.575022718	1.00000	</node>
<node>	-0.728922813	0.617048674	1.00000	</node>
<node>	-0.701474902	0.65644436	1.00000	</node>
<node>	-0.707792091	0.704171074	1.00000	</node>
<node>	-0.706579223	-0.705941953	1.00000	</node>
<node>	-0.636951623	-0.769559059	1.00000	</node>
<node>	-0.651278395	-0.709705756	1.00000	</node>
<node>	-0.715567495	-0.631207667	1.00000	</node>
<node>	-0.685844287	-0.67510866	1.00000	</node>
<node>	-0.71839377	-0.5490899	1.00000	</node>
<node>	-0.660266666	-0.634971469	1.00000	</node>
<node>	-0.63491738	-0.594781061	1.00000	</node>
<node>	-0.662832127	-0.54962072	1.00000	</node>
<node>	-0.71815479	-0.463610983	1.00000	</node>
<node>	-0.691236024	-0.507640144	1.00000	</node>
<node>	-0.71483372	-0.375394997	1.00000	</node>
<node>	-0.662593148	-0.464141804	1.00000	</node>
<node>	-0.635563063	-0.420890004	1.00000	</node>
<node>	-0.662181798	-0.375589174	1.00000	</node>
<node>	-0.714524483	-0.285218253	1.00000	</node>
<node>	-0.687503604	-0.330871528	1.00000	</node>
<node>	-0.720111699	-0.195096664	1.00000	</node>
<node>	-0.661872561	-0.285412431	1.00000	</node>
<node>	-0.635820035	-0.240663131	1.00000	</node>
<node>	-0.664224961	-0.195372521	1.00000	</node>
<node>	-0.72120578	-0.105930021	1.00000	</node>
<node>	-0.695443219	-0.15071003	1.00000	</node>
<node>	-0.714376181	-0.015222546	1.00000	</node>
<node>	-0.665319042	-0.106205877	1.00000	</node>
<node>	-0.637297278	-0.061680163	1.00000	</node>
<node>	-0.662350066	-0.016004819	1.00000	</node>
<node>	-0.711816092	0.076522957	1.00000	</node>
<node>	-0.685644645	0.030198503	1.00000	</node>
<node>	-0.713159889	0.167750664	1.00000	</node>
<node>	-0.659789977	0.075740683	1.00000	</node>
<node>	-0.632651727	0.120870536	1.00000	</node>
<node>	-0.658130302	0.166428148	1.00000	</node>
<node>	-0.706824143	0.257458004	1.00000	</node>
<node>	-0.685328766	0.212113676	1.00000	</node>
<node>	-0.695153865	0.347817038	1.00000	</node>
<node>	-0.651794555	0.256135489	1.00000	</node>
<node>	-0.621624071	0.301464904	1.00000	</node>
<node>	-0.644174533	0.34738748	1.00000	</node>
<node>	-0.689276857	0.438956796	1.00000	</node>
<node>	-0.666038466	0.393724701	1.00000	</node>
<node>	-0.685928996	0.526810689	1.00000	</node>
<node>	-0.638297525	0.438527239	1.00000	</node>
<node>	-0.610581962	0.485725499	1.00000	</node>
<node>	-0.63344712	0.530002438	1.00000	</node>
<node>	-0.682874165	0.60925773	1.00000	</node>
<node>	-0.6578402	0.573053792	1.00000	</node>
<node>	-0.630392289	0.612449479	1.00000	</node>
<node>	-0.611368983	0.668740096	1.00000	</node>
<node>	-0.661743443	0.696380129	1.00000	</node>
<node>	-0.616216687	-0.738725766	1.00000	</node>
<node>	-0.564907937	-0.823934734	1.00000	</node>
<node>	-0.540816436	-0.792644042	1.00000	</node>
<node>	-0.567319324	-0.749132574	1.00000	</node>
<node>	-0.605194173	-0.638682054	1.00000	</node>
<node>	-0.581646096	-0.68927927	1.00000	</node>
<node>	-0.607759634	-0.553331306	1.00000	</node>
<node>	-0.55629681	-0.649088862	1.00000	</node>
<node>	-0.528048253	-0.604453671	1.00000	</node>
<node>	-0.553646586	-0.555900611	1.00000	</node>
<node>	-0.608644297	-0.464919165	1.00000	</node>
<node>	-0.581561333	-0.51074027	1.00000	</node>
<node>	-0.608232947	-0.376366535	1.00000	</node>
<node>	-0.554531249	-0.46748847	1.00000	</node>
<node>	-0.528281856	-0.423402867	1.00000	</node>
<node>	-0.555074706	-0.377344834	1.00000	</node>
<node>	-0.608799155	-0.286316406	1.00000	</node>
<node>	-0.581693441	-0.332044005	1.00000	</node>
<node>	-0.611151555	-0.196276497	1.00000	</node>
<node>	-0.555640914	-0.287294705	1.00000	</node>
<node>	-0.529468603	-0.242648077	1.00000	</node>
<node>	-0.556840938	-0.197048948	1.00000	</node>
<node>	-0.611534718	-0.106460172	1.00000	</node>
<node>	-0.585245864	-0.151758338	1.00000	</node>
<node>	-0.608565742	-0.016259115	1.00000	</node>
<node>	-0.5572241	-0.107232624	1.00000	</node>
<node>	-0.529992033	-0.062550442	1.00000	</node>
<node>	-0.555671233	-0.016927051	1.00000	</node>
<node>	-0.60648028	0.074546082	1.00000	</node>
<node>	-0.580724021	0.028748293	1.00000	</node>
<node>	-0.604820604	0.165233548	1.00000	</node>
<node>	-0.553585771	0.073878145	1.00000	</node>
<node>	-0.526367564	0.119066734	1.00000	</node>
<node>	-0.551540924	0.16480779	1.00000	</node>
<node>	-0.600128695	0.256120576	1.00000	</node>
<node>	-0.577019499	0.210365402	1.00000	</node>
<node>	-0.592508673	0.347372567	1.00000	</node>
<node>	-0.546849015	0.255694818	1.00000	</node>
<node>	-0.51854916	0.301711537	1.00000	</node>
<node>	-0.541829022	0.34830889	1.00000	</node>
<node>	-0.587343571	0.440493404	1.00000	</node>
<node>	-0.564379483	0.394231466	1.00000	</node>
<node>	-0.582493166	0.531968603	1.00000	</node>
<node>	-0.53666392	0.441429727	1.00000	</node>
<node>	-0.510634006	0.490187158	1.00000	</node>
<node>	-0.53519275	0.538963535	1.00000	</node>
<node>	-0.586335018	0.632536159	1.00000	</node>
<node>	-0.558057908	0.583240473	1.00000	</node>
<node>	-0.617686172	0.716466809	1.00000	</node>
<node>	-0.578984809	0.747874426	1.00000	</node>
<node>	-0.539034602	0.639531091	1.00000	</node>
<node>	-0.512001651	0.686153463	1.00000	</node>
<node>	-0.534299619	0.727677958	1.00000	</node>
<node>	-0.629359269	0.775514459	1.00000	</node>
<node>	-0.545972716	0.786725608	1.00000	</node>
<node>	-0.543370282	0.837598688	1.00000	</node>
<node>	-0.503834458	-0.817999706	1.00000	</node>
<node>	-0.487494454	-0.871896448	1.00000	</node>
<node>	-0.506245845	-0.743197546	1.00000	</node>
<node>	-0.463402953	-0.840605756	1.00000	</node>
<node>	-0.427028784	-0.797650657	1.00000	</node>
<node>	-0.451460908	-0.745598176	1.00000	</node>
<node>	-0.504500176	-0.655050887	1.00000	</node>
<node>	-0.477963796	-0.702086707	1.00000	</node>
<node>	-0.501849952	-0.561862636	1.00000	</node>
<node>	-0.449715239	-0.657451517	1.00000	</node>
<node>	-0.423345118	-0.611663074	1.00000	</node>
<node>	-0.449555225	-0.565069988	1.00000	</node>
<node>	-0.501198893	-0.469223972	1.00000	</node>
<node>	-0.475153558	-0.516516928	1.00000	</node>
<node>	-0.50174235	-0.379080337	1.00000	</node>
<node>	-0.448904166	-0.472431325	1.00000	</node>
<node>	-0.42237995	-0.427124128	1.00000	</node>
<node>	-0.448693886	-0.38046691	1.00000	</node>
<node>	-0.502362889	-0.288375675	1.00000	</node>
<node>	-0.475486735	-0.334408877	1.00000	</node>
<node>	-0.503562912	-0.198129918	1.00000	</node>
<node>	-0.449314424	-0.289762248	1.00000	</node>
<node>	-0.423085199	-0.244863887	1.00000	</node>
<node>	-0.449943439	-0.199016046	1.00000	</node>
<node>	-0.50370318	-0.107848607	1.00000	</node>
<node>	-0.477315774	-0.153416917	1.00000	</node>
<node>	-0.502150313	-0.017543035	1.00000	</node>
<node>	-0.450083706	-0.108734735	1.00000	</node>
<node>	-0.42325172	-0.063831993	1.00000	</node>
<node>	-0.449207657	-0.018127942	1.00000	</node>
<node>	-0.500611306	0.073268944	1.00000	</node>
<node>	-0.474886857	0.027495448	1.00000	</node>
<node>	-0.498566458	0.164198588	1.00000	</node>
<node>	-0.44766865	0.072684037	1.00000	</node>
<node>	-0.420747127	0.117998827	1.00000	</node>
<node>	-0.446135065	0.163976659	1.00000	</node>
<node>	-0.495439964	0.255956364	1.00000	</node>
<node>	-0.471308425	0.209717715	1.00000	</node>
<node>	-0.490419971	0.348570436	1.00000	</node>
<node>	-0.44300857	0.255734435	1.00000	</node>
<node>	-0.415954534	0.301824723	1.00000	</node>
<node>	-0.440379236	0.349112866	1.00000	</node>
<node>	-0.487669919	0.443925221	1.00000	</node>
<node>	-0.463659097	0.395710219	1.00000	</node>
<node>	-0.486198748	0.541459028	1.00000	</node>
<node>	-0.437629183	0.44446765	1.00000	</node>
<node>	-0.411562222	0.491089801	1.00000	</node>
<node>	-0.435544608	0.540109562	1.00000	</node>
<node>	-0.483724541	0.636857777	1.00000	</node>
<node>	-0.460103351	0.588885939	1.00000	</node>
<node>	-0.478989558	0.725004645	1.00000	</node>
<node>	-0.4330704	0.635508311	1.00000	</node>
<node>	-0.407476436	0.684628997	1.00000	</node>
<node>	-0.431115498	0.738012145	1.00000	</node>
<node>	-0.498685091	0.81740222	1.00000	</node>
<node>	-0.453413465	0.77953664	1.00000	</node>
<node>	-0.450811031	0.83040972	1.00000	</node>
<node>	-0.450777085	0.89119149	1.00000	</node>
<node>	-0.406735346	-0.912478443	1.00000	</node>
<node>	-0.370361177	-0.869523343	1.00000	</node>
<node>	-0.31881811	-0.94648469	1.00000	</node>
<node>	-0.331745713	-0.900059398	1.00000	</node>
<node>	-0.410688779	-0.851547399	1.00000	</node>
<node>	-0.398746735	-0.756539819	1.00000	</node>
<node>	-0.335699146	-0.839128355	1.00000	</node>
<node>	-0.317700411	-0.798449948	1.00000	</node>
<node>	-0.347255924	-0.758261259	1.00000	</node>
<node>	-0.396808738	-0.658698894	1.00000	</node>
<node>	-0.371688048	-0.706208777	1.00000	</node>
<node>	-0.396648724	-0.566317365	1.00000	</node>
<node>	-0.345317927	-0.660420334	1.00000	</node>
<node>	-0.317866401	-0.613951816	1.00000	</node>
<node>	-0.343812201	-0.567358759	1.00000	</node>
<node>	-0.396334616	-0.474417083	1.00000	</node>
<node>	-0.370022308	-0.520765673	1.00000	</node>
<node>	-0.396124336	-0.382452668	1.00000	</node>
<node>	-0.343498092	-0.475458476	1.00000	</node>
<node>	-0.316976953	-0.430018771	1.00000	</node>
<node>	-0.343388759	-0.383822404	1.00000	</node>
<node>	-0.396209046	-0.290897089	1.00000	</node>
<node>	-0.369702695	-0.337165186	1.00000	</node>
<node>	-0.39683806	-0.200150886	1.00000	</node>
<node>	-0.343473469	-0.292266825	1.00000	</node>
<node>	-0.317108558	-0.246972936	1.00000	</node>
<node>	-0.343640061	-0.200996423	1.00000	</node>
<node>	-0.396864313	-0.109400303	1.00000	</node>
<node>	-0.370498301	-0.155148582	1.00000	</node>
<node>	-0.395988264	-0.01879351	1.00000	</node>
<node>	-0.343666314	-0.11024584	1.00000	</node>
<node>	-0.317062668	-0.065102362	1.00000	</node>
<node>	-0.343184026	-0.019327205	1.00000	</node>
<node>	-0.395022678	0.072225332	1.00000	</node>
<node>	-0.369139963	0.026376846	1.00000	</node>
<node>	-0.393489093	0.163517954	1.00000	</node>
<node>	-0.34221844	0.071691637	1.00000	</node>
<node>	-0.315599189	0.117035638	1.00000	</node>
<node>	-0.341376068	0.163093662	1.00000	</node>
<node>	-0.391822996	0.255586074	1.00000	</node>
<node>	-0.366764007	0.209071494	1.00000	</node>
<node>	-0.389193661	0.348964506	1.00000	</node>
<node>	-0.33970997	0.255161782	1.00000	</node>
<node>	-0.313125402	0.300656204	1.00000	</node>
<node>	-0.338374129	0.347617236	1.00000	</node>
<node>	-0.387551401	0.4428748	1.00000	</node>
<node>	-0.36279883	0.39490538	1.00000	</node>
<node>	-0.385466825	0.538516711	1.00000	</node>
<node>	-0.336731869	0.44152753	1.00000	</node>
<node>	-0.31098164	0.487208281	1.00000	</node>
<node>	-0.336091332	0.53609201	1.00000	</node>
<node>	-0.383855246	0.636657159	1.00000	</node>
<node>	-0.360073718	0.585111772	1.00000	</node>
<node>	-0.381900343	0.739160992	1.00000	</node>
<node>	-0.334479753	0.634232458	1.00000	</node>
<node>	-0.307696831	0.67782304	1.00000	</node>
<node>	-0.327052268	0.728617606	1.00000	</node>
<node>	-0.365128177	0.825648223	1.00000	</node>
<node>	-0.405505459	0.85332591	1.00000	</node>
<node>	-0.350691331	0.782000754	1.00000	</node>
<node>	-0.365094232	0.886429993	1.00000	</node>
<node>	-0.310280103	0.815104837	1.00000	</node>
<node>	-0.274842989	0.86539747	1.00000	</node>
<node>	-0.31039535	0.906958693	1.00000	</node>
<node>	-0.350772632	0.93463638	1.00000	</node>
<node>	-0.284156079	-0.916089702	1.00000	</node>
<node>	-0.224600407	-0.973275242	1.00000	</node>
<node>	-0.23873384	-0.922134599	1.00000	</node>
<node>	-0.279084947	-0.828986003	1.00000	</node>
<node>	-0.251661443	-0.875709307	1.00000	</node>
<node>	-0.290641724	-0.748118907	1.00000	</node>
<node>	-0.233662707	-0.8350309	1.00000	</node>
<node>	-0.208126935	-0.792255485	1.00000	</node>
<node>	-0.235545238	-0.745757672	1.00000	</node>
<node>	-0.29274571	-0.661461699	1.00000	</node>
<node>	-0.265100751	-0.705568983	1.00000	</node>
<node>	-0.291239984	-0.568400124	1.00000	</node>
<node>	-0.237649225	-0.659100465	1.00000	</node>
<node>	-0.211471763	-0.614848659	1.00000	</node>
<node>	-0.238440209	-0.569290359	1.00000	</node>
<node>	-0.290664645	-0.476367361	1.00000	</node>
<node>	-0.264386009	-0.522697302	1.00000	</node>
<node>	-0.290555313	-0.384731289	1.00000	</node>
<node>	-0.237864871	-0.477257597	1.00000	</node>
<node>	-0.211354172	-0.431568825	1.00000	</node>
<node>	-0.237726862	-0.385457755	1.00000	</node>
<node>	-0.290602207	-0.293241033	1.00000	</node>
<node>	-0.264138668	-0.339261388	1.00000	</node>
<node>	-0.290768799	-0.201970632	1.00000	</node>
<node>	-0.237773757	-0.293967499	1.00000	</node>
<node>	-0.211384332	-0.248481291	1.00000	</node>
<node>	-0.237834752	-0.202640481	1.00000	</node>
<node>	-0.290696656	-0.110850641	1.00000	</node>
<node>	-0.264366255	-0.156663968	1.00000	</node>
<node>	-0.290214367	-0.019932006	1.00000	</node>
<node>	-0.237762609	-0.11152049	1.00000	</node>
<node>	-0.211263234	-0.066177309	1.00000	</node>
<node>	-0.237501227	-0.020424299	1.00000	</node>
<node>	-0.289716474	0.071187153	1.00000	</node>
<node>	-0.263622584	0.025350858	1.00000	</node>
<node>	-0.288874102	0.162589178	1.00000	</node>
<node>	-0.237003334	0.070694859	1.00000	</node>
<node>	-0.210525707	0.115992893	1.00000	</node>
<node>	-0.2366029	0.161837527	1.00000	</node>
<node>	-0.288066413	0.254141624	1.00000	</node>
<node>	-0.262379779	0.207895551	1.00000	</node>
<node>	-0.286730572	0.346597078	1.00000	</node>
<node>	-0.235795211	0.253389973	1.00000	</node>
<node>	-0.209456074	0.298594934	1.00000	</node>
<node>	-0.235354887	0.34495653	1.00000	</node>
<node>	-0.28622907	0.439238861	1.00000	</node>
<node>	-0.260603614	0.391917562	1.00000	</node>
<node>	-0.285588533	0.533803341	1.00000	</node>
<node>	-0.234853385	0.437598313	1.00000	</node>
<node>	-0.208792206	0.482070288	1.00000	</node>
<node>	-0.234424062	0.529007557	1.00000	</node>
<node>	-0.283915304	0.626277653	1.00000	</node>
<node>	-0.259533755	0.577891287	1.00000	</node>
<node>	-0.276487819	0.720662802	1.00000	</node>
<node>	-0.232750833	0.621481869	1.00000	</node>
<node>	-0.206326333	0.664621461	1.00000	</node>
<node>	-0.229755597	0.713199581	1.00000	</node>
<node>	-0.260406142	0.821750001	1.00000	</node>
<node>	-0.249111034	0.763994147	1.00000	</node>
<node>	-0.260521389	0.913603858	1.00000	</node>
<node>	-0.21367392	0.814286781	1.00000	</node>
<node>	-0.183461976	0.848642362	1.00000	</node>
<node>	-0.206939638	0.927018495	1.00000	</node>
<node>	-0.169060654	0.892484387	1.00000	</node>
<node>	-0.242491999	0.968579718	1.00000	</node>
<node>	-0.192105771	-0.932894848	1.00000	</node>
<node>	-0.132189818	-0.990147693	1.00000	</node>
<node>	-0.14310988	-0.939575908	1.00000	</node>
<node>	-0.180703432	-0.838978789	1.00000	</node>
<node>	-0.157243313	-0.888435265	1.00000	</node>
<node>	-0.182585963	-0.749705561	1.00000	</node>
<node>	-0.131707541	-0.84565985	1.00000	</node>
<node>	-0.103137465	-0.80138028	1.00000	</node>
<node>	-0.129358543	-0.752290409	1.00000	</node>
<node>	-0.183826803	-0.658955943	1.00000	</node>
<node>	-0.156776845	-0.705792596	1.00000	</node>
<node>	-0.184617788	-0.569145838	1.00000	</node>
<node>	-0.130599383	-0.661540791	1.00000	</node>
<node>	-0.104921041	-0.615745742	1.00000	</node>
<node>	-0.131491545	-0.569318508	1.00000	</node>
<node>	-0.185075536	-0.477898766	1.00000	</node>
<node>	-0.158459992	-0.523760208	1.00000	</node>
<node>	-0.184937528	-0.386098924	1.00000	</node>
<node>	-0.131949294	-0.478071437	1.00000	</node>
<node>	-0.105675651	-0.432321126	1.00000	</node>
<node>	-0.132143076	-0.38651396	1.00000	</node>
<node>	-0.184920792	-0.294501646	1.00000	</node>
<node>	-0.158515766	-0.34040289	1.00000	</node>
<node>	-0.184981788	-0.203174628	1.00000	</node>
<node>	-0.132126341	-0.294916682	1.00000	</node>
<node>	-0.105701857	-0.249271953	1.00000	</node>
<node>	-0.132115543	-0.203543394	1.00000	</node>
<node>	-0.184932833	-0.111990636	1.00000	</node>
<node>	-0.158565964	-0.157702584	1.00000	</node>
<node>	-0.184671451	-0.020894445	1.00000	</node>
<node>	-0.132066588	-0.112359402	1.00000	</node>
<node>	-0.10561875	-0.066899698	1.00000	</node>
<node>	-0.13195433	-0.021285029	1.00000	</node>
<node>	-0.184431817	0.070156598	1.00000	</node>
<node>	-0.158192324	0.02446798	1.00000	</node>
<node>	-0.184031384	0.161299266	1.00000	</node>
<node>	-0.131714697	0.069766014	1.00000	</node>
<node>	-0.105319976	0.115132103	1.00000	</node>
<node>	-0.13157899	0.160710504	1.00000	</node>
<node>	-0.183769441	0.252348861	1.00000	</node>
<node>	-0.157656184	0.206555137	1.00000	</node>
<node>	-0.183329117	0.343915418	1.00000	</node>
<node>	-0.131317047	0.251760099	1.00000	</node>
<node>	-0.104990914	0.296857906	1.00000	</node>
<node>	-0.131215076	0.342346842	1.00000	</node>
<node>	-0.18316675	0.434748989	1.00000	</node>
<node>	-0.157113889	0.388708437	1.00000	</node>
<node>	-0.182737427	0.526158233	1.00000	</node>
<node>	-0.13105271	0.433180413	1.00000	</node>
<node>	-0.104886938	0.477562505	1.00000	</node>
<node>	-0.130947961	0.522981372	1.00000	</node>
<node>	-0.181944784	0.616235094	1.00000	</node>
<node>	-0.156579817	0.569918641	1.00000	</node>
<node>	-0.178949549	0.707952806	1.00000	</node>
<node>	-0.130155318	0.613058233	1.00000	</node>
<node>	-0.10343145	0.655718206	1.00000	</node>
<node>	-0.127429768	0.699832389	1.00000	</node>
<node>	-0.172166868	0.790886507	1.00000	</node>
<node>	-0.150859032	0.748410509	1.00000	</node>
<node>	-0.120647088	0.78276609	1.00000	</node>
<node>	-0.095294866	0.827814283	1.00000	</node>
<node>	-0.127553602	0.869084114	1.00000	</node>
<node>	-0.151031264	0.947460248	1.00000	</node>
<node>	-0.124917748	0.990068344	1.00000	</node>
<node>	-0.09732736	-0.945688111	1.00000	</node>
<node>	-0.043171528	-0.998129947	1.00000	</node>
<node>	-0.043209743	-0.95234822	1.00000	</node>
<node>	-0.079677347	-0.850836756	1.00000	</node>
<node>	-0.054129805	-0.901776435	1.00000	</node>
<node>	-0.077328348	-0.757467315	1.00000	</node>
<node>	-0.025559729	-0.857496865	1.00000	</node>
<node>	-1.96E-05	-0.806556978	1.00000	</node>
<node>	-0.025562245	-0.758965814	1.00000	</node>
<node>	-0.077871083	-0.662582395	1.00000	</node>
<node>	-0.051783322	-0.709875943	1.00000	</node>
<node>	-0.078763245	-0.570360112	1.00000	</node>
<node>	-0.02610498	-0.664080894	1.00000	</node>
<node>	-1.45E-05	-0.616787411	1.00000	</node>
<node>	-0.026101744	-0.570610936	1.00000	</node>
<node>	-0.079060106	-0.478182568	1.00000	</node>
<node>	-0.052672248	-0.524183702	1.00000	</node>
<node>	-0.079253889	-0.386625091	1.00000	</node>
<node>	-0.026398605	-0.478433391	1.00000	</node>
<node>	-7.13E-06	-0.432432498	1.00000	</node>
<node>	-0.02639523	-0.386674627	1.00000	</node>
<node>	-0.079296831	-0.295173197	1.00000	</node>
<node>	-0.052862656	-0.340867461	1.00000	</node>
<node>	-0.079286033	-0.203799909	1.00000	</node>
<node>	-0.026438172	-0.295222732	1.00000	</node>
<node>	-1.70E-06	-0.24952847	1.00000	</node>
<node>	-0.026436403	-0.20393952	1.00000	</node>
<node>	-0.079251881	-0.112611645	1.00000	</node>
<node>	-0.052850089	-0.15821096	1.00000	</node>
<node>	-0.079139623	-0.021537272	1.00000	</node>
<node>	-0.026402251	-0.112751256	1.00000	</node>
<node>	-2.80E-07	-0.067151477	1.00000	</node>
<node>	-0.026402752	-0.021669368	1.00000	</node>
<node>	-0.079080482	0.069443485	1.00000	</node>
<node>	-0.052738332	0.0239453	1.00000	</node>
<node>	-0.078944775	0.160387974	1.00000	</node>
<node>	-0.026343611	0.069311389	1.00000	</node>
<node>	-4.09E-06	0.114810531	1.00000	</node>
<node>	-0.026347109	0.160134626	1.00000	</node>
<node>	-0.078877657	0.251064182	1.00000	</node>
<node>	-0.052606124	0.205713027	1.00000	</node>
<node>	-0.078775686	0.341650926	1.00000	</node>
<node>	-0.026279991	0.250810834	1.00000	</node>
<node>	-1.44E-05	0.296163216	1.00000	</node>
<node>	-0.026287169	0.341142872	1.00000	</node>
<node>	-0.078834076	0.431521954	1.00000	</node>
<node>	-0.052511331	0.386631808	1.00000	</node>
<node>	-0.078729328	0.521322914	1.00000	</node>
<node>	-0.026345559	0.431013901	1.00000	</node>
<node>	-3.48E-05	0.475905391	1.00000	</node>
<node>	-0.026361283	0.519731669	1.00000	</node>
<node>	-0.078066483	0.609401753	1.00000	</node>
<node>	-0.052422306	0.565150536	1.00000	</node>
<node>	-0.075340933	0.696175909	1.00000	</node>
<node>	-0.025698438	0.607810509	1.00000	</node>
<node>	-7.30E-05	0.652043135	1.00000	</node>
<node>	-0.025717726	0.696303682	1.00000	</node>
<node>	-0.07398703	0.785338285	1.00000	</node>
<node>	-0.049716044	0.740417865	1.00000	</node>
<node>	-0.080893544	0.871656308	1.00000	</node>
<node>	-0.024363823	0.785466057	1.00000	</node>
<node>	-3.82E-05	0.830288295	1.00000	</node>
<node>	-0.024215218	0.874085283	1.00000	</node>
<node>	-0.087038764	0.955534236	1.00000	</node>
<node>	-0.056473954	0.915355115	1.00000	</node>
<node>	-0.030360438	0.957963211	1.00000	</node>
<node>	0.000746086	0.998096232	1.00000	</node>
<node>	0.043266827	-0.998127252	1.00000	</node>
<node>	2.60E-05	-0.954218271	1.00000	</node>
<node>	0.043228612	-0.952345525	1.00000	</node>
<node>	0.132199164	-0.990148924	1.00000	</node>
<node>	0.097336981	-0.945682121	1.00000	</node>
<node>	0.025527921	-0.857496657	1.00000	</node>
<node>	0.054096181	-0.90177314	1.00000	</node>
<node>	0.025525406	-0.758965606	1.00000	</node>
<node>	0.079636291	-0.850833253	1.00000	</node>
<node>	0.103094034	-0.801380536	1.00000	</node>
<node>	0.077289686	-0.757467829	1.00000	</node>
<node>	0.02607325	-0.664080959	1.00000	</node>
<node>	0.051747062	-0.709876665	1.00000	</node>
<node>	0.026076486	-0.570611	1.00000	</node>
<node>	0.07783753	-0.662583182	1.00000	</node>
<node>	0.104890573	-0.615747779	1.00000	</node>
<node>	0.078737752	-0.57036088	1.00000	</node>
<node>	0.026380725	-0.478433632	1.00000	</node>
<node>	0.052650519	-0.524184405	1.00000	</node>
<node>	0.0263841	-0.386674868	1.00000	</node>
<node>	0.079041991	-0.478183512	1.00000	</node>
<node>	0.105661164	-0.432322692	1.00000	</node>
<node>	0.079242764	-0.386625748	1.00000	</node>
<node>	0.026432476	-0.295222735	1.00000	</node>
<node>	0.052854666	-0.340867876	1.00000	</node>
<node>	0.026434245	-0.203939522	1.00000	</node>
<node>	0.079291139	-0.295173615	1.00000	</node>
<node>	0.105698557	-0.249272225	1.00000	</node>
<node>	0.079283954	-0.203799538	1.00000	</node>
<node>	0.026401512	-0.112750793	1.00000	</node>
<node>	0.052849251	-0.158210588	1.00000	</node>
<node>	0.026401011	-0.021668905	1.00000	</node>
<node>	0.079251221	-0.112610809	1.00000	</node>
<node>	0.105618386	-0.066897932	1.00000	</node>
<node>	0.079138041	-0.021535358	1.00000	</node>
<node>	0.02633806	0.069312346	1.00000	</node>
<node>	0.052735569	0.023946751	1.00000	</node>
<node>	0.026334561	0.160135584	1.00000	</node>
<node>	0.079075089	0.069445893	1.00000	</node>
<node>	0.105312185	0.115136052	1.00000	</node>
<node>	0.078932482	0.160391284	1.00000	</node>
<node>	0.026257095	0.25081206	1.00000	</node>
<node>	0.052589463	0.205715379	1.00000	</node>
<node>	0.026249917	0.341144098	1.00000	</node>
<node>	0.078855016	0.251067761	1.00000	</node>
<node>	0.104962571	0.296863326	1.00000	</node>
<node>	0.078738526	0.341654829	1.00000	</node>
<node>	0.026287904	0.431015245	1.00000	</node>
<node>	0.052465796	0.386634486	1.00000	</node>
<node>	0.026272179	0.519733014	1.00000	</node>
<node>	0.078776513	0.431525976	1.00000	</node>
<node>	0.10482075	0.477564685	1.00000	</node>
<node>	0.078648182	0.521318591	1.00000	</node>
<node>	0.025571198	0.607791918	1.00000	</node>
<node>	0.052321741	0.565144868	1.00000	</node>
<node>	0.02555191	0.696285091	1.00000	</node>
<node>	0.0779472	0.609377495	1.00000	</node>
<node>	0.103312097	0.655672157	1.00000	</node>
<node>	0.075201265	0.696079242	1.00000	</node>
<node>	0.02423282	0.785367876	1.00000	</node>
<node>	0.049556517	0.740339789	1.00000	</node>
<node>	0.024381426	0.873987102	1.00000	</node>
<node>	0.073882175	0.785162027	1.00000	</node>
<node>	0.095206514	0.827580683	1.00000	</node>
<node>	0.08087317	0.871386747	1.00000	</node>
<node>	0.031310897	0.957917111	1.00000	</node>
<node>	0.056696117	0.915183735	1.00000	</node>
<node>	0.087802641	0.955316756	1.00000	</node>
<node>	0.12521492	0.990108391	1.00000	</node>
<node>	0.143066733	-0.939576539	1.00000	</node>
<node>	0.224533442	-0.973291918	1.00000	</node>
<node>	0.192050201	-0.93290231	1.00000	</node>
<node>	0.131662294	-0.845657019	1.00000	</node>
<node>	0.157188018	-0.888435507	1.00000	</node>
<node>	0.12931569	-0.752291595	1.00000	</node>
<node>	0.180645762	-0.83898279	1.00000	</node>
<node>	0.208072369	-0.792263576	1.00000	</node>
<node>	0.182540084	-0.74970965	1.00000	</node>
<node>	0.130564384	-0.661543485	1.00000	</node>
<node>	0.156735736	-0.705796943	1.00000	</node>
<node>	0.131464605	-0.569321183	1.00000	</node>
<node>	0.183788778	-0.65896154	1.00000	</node>
<node>	0.211437361	-0.614856651	1.00000	</node>
<node>	0.184589747	-0.569150974	1.00000	</node>
<node>	0.131930957	-0.478073464	1.00000	</node>
<node>	0.158436926	-0.523764075	1.00000	</node>
<node>	0.13213173	-0.3865157	1.00000	</node>
<node>	0.185056099	-0.477903254	1.00000	</node>
<node>	0.211338781	-0.431573934	1.00000	</node>
<node>	0.184926107	-0.386101808	1.00000	</node>
<node>	0.132120748	-0.294917367	1.00000	</node>
<node>	0.158507707	-0.340404865	1.00000	</node>
<node>	0.132113563	-0.20354329	1.00000	</node>
<node>	0.184915125	-0.294503475	1.00000	</node>
<node>	0.211381165	-0.248482712	1.00000	</node>
<node>	0.184979973	-0.203174425	1.00000	</node>
<node>	0.132066124	-0.112357726	1.00000	</node>
<node>	0.158565369	-0.157701738	1.00000	</node>
<node>	0.131952944	-0.021282275	1.00000	</node>
<node>	0.184932534	-0.111988861	1.00000	</node>
<node>	0.211263387	-0.066174131	1.00000	</node>
<node>	0.184670458	-0.02089031	1.00000	</node>
<node>	0.131709694	0.069770457	1.00000	</node>
<node>	0.158190112	0.024472263	1.00000	</node>
<node>	0.131567087	0.160715848	1.00000	</node>
<node>	0.184427208	0.070162422	1.00000	</node>
<node>	0.210518854	0.116001026	1.00000	</node>
<node>	0.184020132	0.161307482	1.00000	</node>
<node>	0.13129494	0.251766645	1.00000	</node>
<node>	0.157640429	0.206562713	1.00000	</node>
<node>	0.13117845	0.342353714	1.00000	</node>
<node>	0.183747985	0.252358279	1.00000	</node>
<node>	0.209429986	0.298606757	1.00000	</node>
<node>	0.183294805	0.343924645	1.00000	</node>
<node>	0.130998642	0.433183925	1.00000	</node>
<node>	0.15707076	0.388716148	1.00000	</node>
<node>	0.130870311	0.52297654	1.00000	</node>
<node>	0.183114997	0.434754857	1.00000	</node>
<node>	0.208735132	0.482075469	1.00000	</node>
<node>	0.182670619	0.526152779	1.00000	</node>
<node>	0.130062639	0.613025108	1.00000	</node>
<node>	0.156498051	0.569906685	1.00000	</node>
<node>	0.127316704	0.699726856	1.00000	</node>
<node>	0.181862947	0.616201347	1.00000	</node>
<node>	0.206242592	0.664587108	1.00000	</node>
<node>	0.178860469	0.70788517	1.00000	</node>
<node>	0.120530211	0.782552596	1.00000	</node>
<node>	0.150749637	0.748292255	1.00000	</node>
<node>	0.127521206	0.868777316	1.00000	</node>
<node>	0.172073976	0.79071091	1.00000	</node>
<node>	0.183281423	0.848509799	1.00000	</node>
<node>	0.168948078	0.892315863	1.00000	</node>
<node>	0.15060014	0.947375016	1.00000	</node>
<node>	0.238654727	-0.922150886	1.00000	</node>
<node>	0.318719438	-0.946518472	1.00000	</node>
<node>	0.284067946	-0.916115912	1.00000	</node>
<node>	0.233598093	-0.835042064	1.00000	</node>
<node>	0.251584705	-0.875726304	1.00000	</node>
<node>	0.235492414	-0.745768923	1.00000	</node>
<node>	0.279011311	-0.82900709	1.00000	</node>
<node>	0.317626891	-0.798476696	1.00000	</node>
<node>	0.290583634	-0.748137306	1.00000	</node>
<node>	0.237608713	-0.659110109	1.00000	</node>
<node>	0.26505135	-0.705583381	1.00000	</node>
<node>	0.238409682	-0.569299543	1.00000	</node>
<node>	0.292699933	-0.661478492	1.00000	</node>
<node>	0.317826034	-0.613969827	1.00000	</node>
<node>	0.291207744	-0.568413257	1.00000	</node>
<node>	0.23784475	-0.477264545	1.00000	</node>
<node>	0.264360131	-0.522707579	1.00000	</node>
<node>	0.237714758	-0.385463099	1.00000	</node>
<node>	0.290642813	-0.476378259	1.00000	</node>
<node>	0.316959758	-0.430030013	1.00000	</node>
<node>	0.290542819	-0.3847388	1.00000	</node>
<node>	0.237768123	-0.29397021	1.00000	</node>
<node>	0.264130145	-0.339266674	1.00000	</node>
<node>	0.237832971	-0.20264116	1.00000	</node>
<node>	0.290596185	-0.29324591	1.00000	</node>
<node>	0.317105357	-0.246977204	1.00000	</node>
<node>	0.290767158	-0.201971871	1.00000	</node>
<node>	0.237762632	-0.111518143	1.00000	</node>
<node>	0.264365966	-0.156663584	1.00000	</node>
<node>	0.237500556	-0.020419593	1.00000	</node>
<node>	0.29069682	-0.110848855	1.00000	</node>
<node>	0.317063334	-0.065098461	1.00000	</node>
<node>	0.290214186	-0.019925972	1.00000	</node>
<node>	0.236999273	0.070702832	1.00000	</node>
<node>	0.263621256	0.025357849	1.00000	</node>
<node>	0.236592197	0.161847892	1.00000	</node>
<node>	0.289712903	0.071196453	1.00000	</node>
<node>	0.315593609	0.117048114	1.00000	</node>
<node>	0.288864392	0.162602462	1.00000	</node>
<node>	0.235775476	0.253402825	1.00000	</node>
<node>	0.262365669	0.207908917	1.00000	</node>
<node>	0.235322296	0.344969191	1.00000	</node>
<node>	0.288047671	0.254157395	1.00000	</node>
<node>	0.313102835	0.300675741	1.00000	</node>
<node>	0.286701452	0.346614893	1.00000	</node>
<node>	0.23480725	0.437607691	1.00000	</node>
<node>	0.26056627	0.391932781	1.00000	</node>
<node>	0.234362872	0.529005614	1.00000	</node>
<node>	0.286186406	0.439253394	1.00000	</node>
<node>	0.310932931	0.487228992	1.00000	</node>
<node>	0.285531325	0.533816273	1.00000	</node>
<node>	0.232678003	0.621468684	1.00000	</node>
<node>	0.259466811	0.577893583	1.00000	</node>
<node>	0.229675525	0.713152507	1.00000	</node>
<node>	0.283846456	0.626279344	1.00000	</node>
<node>	0.307603699	0.677850973	1.00000	</node>
<node>	0.276372327	0.720685803	1.00000	</node>
<node>	0.213500849	0.814249458	1.00000	</node>
<node>	0.248990204	0.763983865	1.00000	</node>
<node>	0.206360357	0.927107499	1.00000	</node>
<node>	0.260197651	0.821782754	1.00000	</node>
<node>	0.274565923	0.865465515	1.00000	</node>
<node>	0.260094941	0.913698391	1.00000	</node>
<node>	0.241747002	0.968757543	1.00000	</node>
<node>	0.331649416	-0.90009389	1.00000	</node>
<node>	0.370264995	-0.869563497	1.00000	</node>
<node>	0.406625277	-0.912527784	1.00000	</node>
<node>	0.335613503	-0.839160936	1.00000	</node>
<node>	0.347185826	-0.758291153	1.00000	</node>
<node>	0.410589365	-0.851594829	1.00000	</node>
<node>	0.426938072	-0.797697669	1.00000	</node>
<node>	0.398670486	-0.7565781	1.00000	</node>
<node>	0.345268671	-0.660443098	1.00000	</node>
<node>	0.371627229	-0.706238711	1.00000	</node>
<node>	0.343776483	-0.567377863	1.00000	</node>
<node>	0.39675333	-0.658730046	1.00000	</node>
<node>	0.423297347	-0.611695027	1.00000	</node>
<node>	0.396610754	-0.566342039	1.00000	</node>
<node>	0.343475139	-0.475473046	1.00000	</node>
<node>	0.369992465	-0.520785468	1.00000	</node>
<node>	0.343375145	-0.383833587	1.00000	</node>
<node>	0.39630941	-0.474437222	1.00000	</node>
<node>	0.422360468	-0.427144361	1.00000	</node>
<node>	0.396110226	-0.382467395	1.00000	</node>
<node>	0.343467378	-0.292273667	1.00000	</node>
<node>	0.369693287	-0.337176182	1.00000	</node>
<node>	0.343638352	-0.200999628	1.00000	</node>
<node>	0.396202459	-0.290907475	1.00000	</node>
<node>	0.423081524	-0.24487291	1.00000	</node>
<node>	0.396836201	-0.200155361	1.00000	</node>
<node>	0.343666668	-0.110243901	1.00000	</node>
<node>	0.370498003	-0.155150029	1.00000	</node>
<node>	0.343184034	-0.019321018	1.00000	</node>
<node>	0.396864518	-0.109399635	1.00000	</node>
<node>	0.423252512	-0.06382841	1.00000	</node>
<node>	0.395988669	-0.018786366	1.00000	</node>
<node>	0.342215592	0.071703131	1.00000	</node>
<node>	0.36913952	0.026386122	1.00000	</node>
<node>	0.341367082	0.163109139	1.00000	</node>
<node>	0.395020227	0.072237783	1.00000	</node>
<node>	0.420742728	0.118015398	1.00000	</node>
<node>	0.39348115	0.16353688	1.00000	</node>
<node>	0.339693028	0.255181833	1.00000	</node>
<node>	0.366751933	0.209091229	1.00000	</node>
<node>	0.338346809	0.347639332	1.00000	</node>
<node>	0.391807097	0.255609575	1.00000	</node>
<node>	0.415934691	0.301854256	1.00000	</node>
<node>	0.389167485	0.348994549	1.00000	</node>
<node>	0.336691952	0.441554082	1.00000	</node>
<node>	0.362766101	0.394933701	1.00000	</node>
<node>	0.336036871	0.536116961	1.00000	</node>
<node>	0.387512627	0.442909299	1.00000	</node>
<node>	0.41151294	0.491136295	1.00000	</node>
<node>	0.385405703	0.538566752	1.00000	</node>
<node>	0.334392507	0.634275871	1.00000	</node>
<node>	0.360004097	0.585154034	1.00000	</node>
<node>	0.326918378	0.72868233	1.00000	</node>
<node>	0.383761339	0.636725662	1.00000	</node>
<node>	0.407359181	0.684715971	1.00000	</node>
<node>	0.381744332	0.739260081	1.00000	</node>
<node>	0.310055278	0.815199922	1.00000	</node>
<node>	0.35051296	0.782094911	1.00000	</node>
<node>	0.309952569	0.907115559	1.00000	</node>
<node>	0.364881233	0.825777673	1.00000	</node>
<node>	0.364767335	0.88657507	1.00000	</node>
<node>	0.350296352	0.934807945	1.00000	</node>
<node>	0.463298354	-0.840661956	1.00000	</node>
<node>	0.48738219	-0.871959322	1.00000	</node>
<node>	0.451379475	-0.745645227	1.00000	</node>
<node>	0.503730897	-0.818062162	1.00000	</node>
<node>	0.540710624	-0.792715538	1.00000	</node>
<node>	0.506158856	-0.743255185	1.00000	</node>
<node>	0.449655906	-0.65749064	1.00000	</node>
<node>	0.477891269	-0.702135616	1.00000	</node>
<node>	0.449513329	-0.565102633	1.00000	</node>
<node>	0.504435286	-0.655100597	1.00000	</node>
<node>	0.527993659	-0.604502377	1.00000	</node>
<node>	0.501805952	-0.561902498	1.00000	</node>
<node>	0.448877794	-0.472456783	1.00000	</node>
<node>	0.475119359	-0.51654951	1.00000	</node>
<node>	0.44867861	-0.380486956	1.00000	</node>
<node>	0.501170417	-0.469256649	1.00000	</node>
<node>	0.528259609	-0.423434586	1.00000	</node>
<node>	0.501726158	-0.379104781	1.00000	</node>
<node>	0.449307433	-0.289775425	1.00000	</node>
<node>	0.475475916	-0.334427815	1.00000	</node>
<node>	0.449941176	-0.199023311	1.00000	</node>
<node>	0.502354981	-0.28839325	1.00000	</node>
<node>	0.52946384	-0.242663398	1.00000	</node>
<node>	0.503560196	-0.198139176	1.00000	</node>
<node>	0.450083847	-0.108734538	1.00000	</node>
<node>	0.477314873	-0.153421627	1.00000	</node>
<node>	0.449207998	-0.018121269	1.00000	</node>
<node>	0.503702867	-0.107850402	1.00000	</node>
<node>	0.529992454	-0.062548518	1.00000	</node>
<node>	0.50215082	-0.017536033	1.00000	</node>
<node>	0.447666656	0.07269839	1.00000	</node>
<node>	0.474886977	0.027506011	1.00000	</node>
<node>	0.446127579	0.163997488	1.00000	</node>
<node>	0.500609478	0.073283626	1.00000	</node>
<node>	0.526363618	0.119086378	1.00000	</node>
<node>	0.498559188	0.164222627	1.00000	</node>
<node>	0.442993595	0.255763651	1.00000	</node>
<node>	0.471297611	0.209744109	1.00000	</node>
<node>	0.440353983	0.349148625	1.00000	</node>
<node>	0.495425204	0.25598879	1.00000	</node>
<node>	0.518529856	0.30175111	1.00000	</node>
<node>	0.490393903	0.348614627	1.00000	</node>
<node>	0.43758709	0.444515914	1.00000	</node>
<node>	0.463626697	0.395754921	1.00000	</node>
<node>	0.435480166	0.540173367	1.00000	</node>
<node>	0.48762701	0.443981916	1.00000	</node>
<node>	0.510580999	0.490253715	1.00000	</node>
<node>	0.486130955	0.541532684	1.00000	</node>
<node>	0.432970771	0.635594133	1.00000	</node>
<node>	0.460023718	0.588963141	1.00000	</node>
<node>	0.430953764	0.738128552	1.00000	</node>
<node>	0.48362156	0.63695345	1.00000	</node>
<node>	0.511881116	0.686260146	1.00000	</node>
<node>	0.478842712	0.725118616	1.00000	</node>
<node>	0.450588479	0.830543836	1.00000	</node>
<node>	0.405225017	0.853470059	1.00000	</node>
<node>	0.453227863	0.779662726	1.00000	</node>
<node>	0.450474581	0.891341233	1.00000	</node>
<node>	0.498477427	0.817533901	1.00000	</node>
<node>	0.543163569	0.837730313	1.00000	</node>
<node>	0.56479446	-0.824012904	1.00000	</node>
<node>	0.567222418	-0.749205927	1.00000	</node>
<node>	0.636838107	-0.76965316	1.00000	</node>
<node>	0.616117047	-0.738808189	1.00000	</node>
<node>	0.556229023	-0.649147353	1.00000	</node>
<node>	0.581565278	-0.689347836	1.00000	</node>
<node>	0.553599689	-0.555949253	1.00000	</node>
<node>	0.605123651	-0.638749615	1.00000	</node>
<node>	0.634856995	-0.594848833	1.00000	</node>
<node>	0.607710411	-0.55338805	1.00000	</node>
<node>	0.554501174	-0.467527312	1.00000	</node>
<node>	0.581522704	-0.510788171	1.00000	</node>
<node>	0.555056915	-0.377375445	1.00000	</node>
<node>	0.608611896	-0.464966108	1.00000	</node>
<node>	0.635537356	-0.420934748	1.00000	</node>
<node>	0.608213951	-0.376402235	1.00000	</node>
<node>	0.555632323	-0.287315788	1.00000	</node>
<node>	0.5816805	-0.33207243	1.00000	</node>
<node>	0.556837538	-0.197061714	1.00000	</node>
<node>	0.608789359	-0.286342578	1.00000	</node>
<node>	0.635813702	-0.240686006	1.00000	</node>
<node>	0.611147502	-0.196291945	1.00000	</node>
<node>	0.55722348	-0.107235607	1.00000	</node>
<node>	0.585243858	-0.151767723	1.00000	</node>
<node>	0.555671433	-0.016921238	1.00000	</node>
<node>	0.611533444	-0.106465839	1.00000	</node>
<node>	0.637296952	-0.061681357	1.00000	</node>
<node>	0.608565912	-0.016253784	1.00000	</node>
<node>	0.553583939	0.073893999	1.00000	</node>
<node>	0.580724279	0.028758701	1.00000	</node>
<node>	0.55153365	0.164833	1.00000	</node>
<node>	0.606478419	0.074561453	1.00000	</node>
<node>	0.63264762	0.120891337	1.00000	</node>
<node>	0.604813085	0.165260567	1.00000	</node>
<node>	0.546833872	0.255731569	1.00000	</node>
<node>	0.577008655	0.210396815	1.00000	</node>
<node>	0.541802571	0.348357406	1.00000	</node>
<node>	0.600113307	0.256159136	1.00000	</node>
<node>	0.621604459	0.301510155	1.00000	</node>
<node>	0.592481917	0.347424269	1.00000	</node>
<node>	0.536620606	0.441492721	1.00000	</node>
<node>	0.564345963	0.394287786	1.00000	</node>
<node>	0.535124551	0.539043489	1.00000	</node>
<node>	0.587299952	0.440559584	1.00000	</node>
<node>	0.610529855	0.485799216	1.00000	</node>
<node>	0.582428219	0.532050067	1.00000	</node>
<node>	0.538934063	0.639629154	1.00000	</node>
<node>	0.557978175	0.583329036	1.00000	</node>
<node>	0.534155215	0.72779432	1.00000	</node>
<node>	0.578841357	0.747990733	1.00000	</node>
<node>	0.586237731	0.632635732	1.00000	</node>
<node>	0.61126284	0.668844227	1.00000	</node>
<node>	0.617565755	0.716576435	1.00000	</node>
<node>	0.545802953	0.786849203	1.00000	</node>
<node>	0.629213492	0.775631319	1.00000	</node>
<node>	0.651180966	-0.709795068	1.00000	</node>
<node>	0.706476325	-0.706044598	1.00000	</node>
<node>	0.66019325	-0.635049316	1.00000	</node>
<node>	0.685755265	-0.675199627	1.00000	</node>
<node>	0.66278001	-0.549687751	1.00000	</node>
<node>	0.715488609	-0.631298846	1.00000	</node>
<node>	0.746860656	-0.593027646	1.00000	</node>
<node>	0.718338914	-0.549165988	1.00000	</node>
<node>	0.662558886	-0.464195608	1.00000	</node>
<node>	0.69119233	-0.507705205	1.00000	</node>
<node>	0.662160941	-0.375631734	1.00000	</node>
<node>	0.718117791	-0.463673845	1.00000	</node>
<node>	0.743558094	-0.42082147	1.00000	</node>
<node>	0.714811438	-0.3754429	1.00000	</node>
<node>	0.661861879	-0.285442648	1.00000	</node>
<node>	0.687488033	-0.330910386	1.00000	</node>
<node>	0.664220022	-0.195392016	1.00000	</node>
<node>	0.714512376	-0.285253814	1.00000	</node>
<node>	0.740675773	-0.239217408	1.00000	</node>
<node>	0.720106081	-0.195119553	1.00000	</node>
<node>	0.66531733	-0.106213473	1.00000	</node>
<node>	0.695439881	-0.150725493	1.00000	</node>
<node>	0.662349798	-0.016001418	1.00000	</node>
<node>	0.721203389	-0.105941011	1.00000	</node>
<node>	0.7447869	-0.062335358	1.00000	</node>
<node>	0.714375861	-0.015220525	1.00000	</node>
<node>	0.65978796	0.075756039	1.00000	</node>
<node>	0.685644821	0.030207049	1.00000	</node>
<node>	0.658122626	0.166455152	1.00000	</node>
<node>	0.711814022	0.076536932	1.00000	</node>
<node>	0.739208235	0.124780092	1.00000	</node>
<node>	0.713152378	0.167777691	1.00000	</node>
<node>	0.651779242	0.256175402	1.00000	</node>
<node>	0.685317842	0.212146921	1.00000	</node>
<node>	0.644147852	0.347440535	1.00000	</node>
<node>	0.706808995	0.25749794	1.00000	</node>
<node>	0.724000206	0.302417658	1.00000	</node>
<node>	0.695128069	0.34787034	1.00000	</node>
<node>	0.638255213	0.438594281	1.00000	</node>
<node>	0.666005527	0.393784454	1.00000	</node>
<node>	0.633383479	0.530084764	1.00000	</node>
<node>	0.68923543	0.439024086	1.00000	</node>
<node>	0.713601507	0.485289931	1.00000	</node>
<node>	0.685870405	0.526890895	1.00000	</node>
<node>	0.630306952	0.612544109	1.00000	</node>
<node>	0.657768768	0.573141746	1.00000	</node>
<node>	0.661634976	0.696484812	1.00000	</node>
<node>	0.682793877	0.60935024	1.00000	</node>
<node>	0.701385596	0.656541451	1.00000	</node>
<node>	0.70768851	0.70427366	1.00000	</node>
<node>	0.772422672	-0.633177957	1.00000	</node>
<node>	0.775272977	-0.551045099	1.00000	</node>
<node>	0.831794283	-0.552774031	1.00000	</node>
<node>	0.772191538	-0.464331067	1.00000	</node>
<node>	0.80327254	-0.508912373	1.00000	</node>
<node>	0.768885185	-0.376100123	1.00000	</node>
<node>	0.828712844	-0.466059999	1.00000	</node>
<node>	0.852643828	-0.42059699	1.00000	</node>
<node>	0.819959514	-0.377711421	1.00000	</node>
<node>	0.766301926	-0.284685146	1.00000	</node>
<node>	0.791212858	-0.332332851	1.00000	</node>
<node>	0.771895632	-0.194550885	1.00000	</node>
<node>	0.817376256	-0.286296445	1.00000	</node>
<node>	0.838173231	-0.24415098	1.00000	</node>
<node>	0.832111533	-0.195930356	1.00000	</node>
<node>	0.774909451	-0.106847377	1.00000	</node>
<node>	0.811541842	-0.151832502	1.00000	</node>
<node>	0.768081923	-0.016126891	1.00000	</node>
<node>	0.835125353	-0.108226849	1.00000	</node>
<node>	0.850020619	-0.059764997	1.00000	</node>
<node>	0.816650749	-0.015197811	1.00000	</node>
<node>	0.765065096	0.079231101	1.00000	</node>
<node>	0.786239709	0.031917022	1.00000	</node>
<node>	0.766403452	0.17047186	1.00000	</node>
<node>	0.813633922	0.080160182	1.00000	</node>
<node>	0.843912796	0.126284128	1.00000	</node>
<node>	0.825714641	0.174125986	1.00000	</node>
<node>	0.757538806	0.258389178	1.00000	</node>
<node>	0.799658784	0.217123585	1.00000	</node>
<node>	0.745857881	0.348761577	1.00000	</node>
<node>	0.816849996	0.262043303	1.00000	</node>
<node>	0.819169317	0.310628735	1.00000	</node>
<node>	0.795535542	0.352053989	1.00000	</node>
<node>	0.741351821	0.440480103	1.00000	</node>
<node>	0.766663405	0.397506671	1.00000	</node>
<node>	0.737986796	0.528346913	1.00000	</node>
<node>	0.791029482	0.443772516	1.00000	</node>
<node>	0.818609142	0.488570383	1.00000	</node>
<node>	0.790072653	0.5335057	1.00000	</node>
<node>	0.728847412	0.617139088	1.00000	</node>
<node>	0.762341551	0.575106665	1.00000	</node>
<node>	0.780933269	0.622297875	1.00000	</node>
<node>	0.88372483	-0.465178296	1.00000	</node>
<node>	0.874971501	-0.376829719	1.00000	</node>
<node>	0.927039819	-0.371321217	1.00000	</node>
<node>	0.863084163	-0.291798685	1.00000	</node>
<node>	0.894355506	-0.328435649	1.00000	</node>
<node>	0.877819441	-0.201432597	1.00000	</node>
<node>	0.915152482	-0.286290184	1.00000	</node>
<node>	0.930061723	-0.23316746	1.00000	</node>
<node>	0.88665301	-0.104750122	1.00000	</node>
<node>	0.924000025	-0.184946836	1.00000	</node>
<node>	0.932141218	-0.137627978	1.00000	</node>
<node>	0.868178406	-0.011721084	1.00000	</node>
<node>	0.947036485	-0.089166127	1.00000	</node>
<node>	0.950686801	-0.037489172	1.00000	</node>
<node>	0.911961921	-0.010685546	1.00000	</node>
<node>	0.865087409	0.078970048	1.00000	</node>
<node>	0.878592051	0.033881641	1.00000	</node>
<node>	0.877168128	0.172935852	1.00000	</node>
<node>	0.908870925	0.080005587	1.00000	</node>
<node>	0.945531212	0.108885946	1.00000	</node>
<node>	0.938009609	0.16042424	1.00000	</node>
<node>	0.861289295	0.269363143	1.00000	</node>
<node>	0.919811454	0.208266098	1.00000	</node>
<node>	0.908030723	0.255281845	1.00000	</node>
<node>	0.839974841	0.359373829	1.00000	</node>
<node>	0.910350044	0.303867277	1.00000	</node>
<node>	0.891196352	0.356354502	1.00000	</node>
<node>	0.843920726	0.44559695	1.00000	</node>
<node>	0.867562577	0.397779756	1.00000	</node>
<node>	0.842963897	0.535330135	1.00000	</node>
<node>	0.895142237	0.442577623	1.00000	</node>
<node>	0.961333065	-0.269804423	1.00000	</node>
<node>	0.9843835	-0.169362841	1.00000	</node>
<node>	0.996175009	-0.070367029	1.00000	</node>
<node>	0.961100446	0.008113552	1.00000	</node>
<node>	0.997760734	0.036993911	1.00000	</node>
<node>	0.959035854	0.063797538	1.00000	</node>
<node>	0.988174538	0.144216191	1.00000	</node>
<node>	0.968872204	0.242770233	1.00000	</node>
<node>	0.93793778	0.342273204	1.00000	</node>



    </nodes>
	
    <edgeinfos>
